{
    "account_id": 1773946733001,
    "archive_master": true,
    "brightcove_standard": false,
    "digital_master": {
        "distribute": false,
        "rendition": "av0"
    },
    "keep_renditions": true,
    "name": "nondrm-av0-no-distribute",
    "packages": [],
    "renditions": [
        {
            "media_type": "video",
            "reference_id": "av0",
            "format": "mp4",
            "audio_codec": "aac",
            "audio_bitrate": 512,
            "video_codec": "h264",
            "speed": 3,
            "video_bitrate": 8192,
            "decoder_bitrate_cap": 16384,
            "decoder_buffer_size": 16384,
            "keyframe_rate": 0.5,
            "max_frame_rate": 30,
            "width": 3840,
            "height": 2160,
            "h264_profile": "baseline"
        },
        {
            "media_type": "video",
            "audio_bitrate": 64,
            "audio_codec": "aac",
            "format": "mp4",
            "h264_profile": "baseline",
            "height": 240,
            "keyframe_rate": 0.5,
            "max_frame_rate": 30.0,
            "media_type": "video",
            "reference_id": "av1",
            "speed": 3,
            "video_bitrate": 270,
            "video_codec": "h264",
            "width": 320
        },
        {
            "format": "png",
            "height": 360,
            "label": "poster",
            "media_type": "image",
            "reference_id": "img0",
            "width": 480
        },
        {
            "format": "png",
            "height": 90,
            "label": "thumbnail",
            "media_type": "image",
            "reference_id": "img1",
            "width": 160
        }
    ]
}
