{
  "PlatformDeliverySecurity" : {
    "RTMPe VOD Flash" : [
      {
        "cdnIntegration" : "BC CDN",
        "actualCDN" : "Limelight Flash Streaming",
        "yesPossible" : "yes",
        "note": ""
      },
      {
        "cdnIntegration" : "BC CDN",
        "actualCDN" : "Akamai Flash Streaming",
        "yesPossible" : "yes",
        "note": ""
      },
      {
        "cdnIntegration" : "BYO CDN",
        "actualCDN" : "Limelight Flash Streaming",
        "yesPossible" : "yes",
        "note": ""
      },
      {
        "cdnIntegration" : "BYO CDN",
        "actualCDN" : "Akamai Flash Streaming",
        "yesPossible" : "yes",
        "note": ""
      },
      {
        "cdnIntegration" : "BYO CDN",
        "actualCDN" : "ChinaCache Flash Streaming",
        "yesPossible" : "yes",
        "note": "China delivery only. Requires another CDN for outside China. Must have multiple accounts, and media sharing is not functional."
      },
      {
        "cdnIntegration" : "BYO CDN",
        "actualCDN" : "Jstream Flash Streaming",
        "yesPossible" : "yes",
        "note": ""
      },
      {
        "cdnIntegration" : "BYO CDN",
        "actualCDN" : "Telefonica Flash Streaming",
        "yesPossible" : "yes",
        "note": ""
      },
      {
        "cdnIntegration" : "Remote Assets",
        "actualCDN" : "Flash Streaming",
        "yesPossible" : "yes",
        "note": "Capability for remote assets delivery is dependent on the server delivering the video.  Brightcove has no control over these delivery and security mechanisms."
      },
      {
        "cdnIntegration" : "Remote Assets",
        "actualCDN" : "HTTP Streaming",
        "yesPossible" : "yes",
        "note": "Capability for remote assets delivery is dependent on the server delivering the video.  Brightcove has no control over these delivery and security mechanisms."
      }
    ],
    "SWFv VOD Flash" : [
      {
        "cdnIntegration" : "BC CDN",
        "actualCDN" : "Limelight Flash Streaming",
        "yesPossible" : "yes",
        "note": ""
      },
      {
        "cdnIntegration" : "BC CDN",
        "actualCDN" : "Akamai Flash Streaming",
        "yesPossible" : "yes",
        "note": ""
      },
      {
        "cdnIntegration" : "BYO CDN",
        "actualCDN" : "Limelight Flash Streaming",
        "yesPossible" : "possible",
        "note": ""
      },
      {
        "cdnIntegration" : "BYO CDN",
        "actualCDN" : "Akamai Flash Streaming",
        "yesPossible" : "possible",
        "note": ""
      },
      {
        "cdnIntegration" : "BYO CDN",
        "actualCDN" : "ChinaCache Flash Streaming",
        "yesPossible" : "possible",
        "note": "China delivery only. Requires another CDN for outside China. Must have multiple accounts, and media sharing is not functional."
      },
      {
        "cdnIntegration" : "BYO CDN",
        "actualCDN" : "Telefonica Flash Streaming",
        "yesPossible" : "possible",
        "note": ""
      },
      {
        "cdnIntegration" : "Remote Assets",
        "actualCDN" : "HTTP Streaming",
        "yesPossible" : "yes",
        "note": "Capability for remote assets delivery is dependent on the server delivering the video.  Brightcove has no control over these delivery and security mechanisms."
      }
    ],
    "TTL VOD Flash" : [
      {
        "cdnIntegration" : "BC CDN",
        "actualCDN" : "Limelight Flash Streaming",
        "yesPossible" : "yes",
        "note": ""
      },
      {
        "cdnIntegration" : "BC CDN",
        "actualCDN" : "Akamai Flash Streaming",
        "yesPossible" : "yes",
        "note": ""
      },
      {
        "cdnIntegration" : "BC CDN",
        "actualCDN" : "Akamai HD",
        "yesPossible" : "yes",
        "note": ""
      },
      {
        "cdnIntegration" : "BC CDN",
        "actualCDN" : "Akamai PD",
        "yesPossible" : "yes",
        "note": ""
      },
      {
        "cdnIntegration" : "BC CDN",
        "actualCDN" : "Akamai HD HTTPs",
        "yesPossible" : "yes",
        "note": ""
      },
        {
        "cdnIntegration" : "BC CDN",
        "actualCDN" : "Akamai HD 2.0",
        "yesPossible" : "yes",
        "note": ""
      },
	  {
        "cdnIntegration" : "BYO CDN",
        "actualCDN" : "Limelight Flash Streaming",
        "yesPossible" : "yes",
        "note": ""
      },
      {
        "cdnIntegration" : "BYO CDN",
        "actualCDN" : "Limelight PD",
        "yesPossible" : "yes",
        "note": ""
      },
      {
        "cdnIntegration" : "BYO CDN",
        "actualCDN" : "Akamai Flash Streaming",
        "yesPossible" : "yes",
        "note": ""
      },
      {
        "cdnIntegration" : "BYO CDN",
        "actualCDN" : "Akamai HD",
        "yesPossible" : "yes",
        "note": ""
      },
      {
        "cdnIntegration" : "BYO CDN",
        "actualCDN" : "Akamai PD",
        "yesPossible" : "yes",
        "note": ""
      },
      {
        "cdnIntegration" : "BYO CDN",
        "actualCDN" : "Akamai HD 2.0",
        "yesPossible" : "yes",
        "note": ""
      },
      {
        "cdnIntegration" : "BYO CDN",
        "actualCDN" : "Level 3 PD",
        "yesPossible" : "possible",
        "note": ""
      },
      {
        "cdnIntegration" : "BYO CDN",
        "actualCDN" : "Level 3 HTTP Streaming",
        "yesPossible" : "possible",
        "note": ""
      },
      {
        "cdnIntegration" : "BYO CDN",
        "actualCDN" : "Highwinds PD",
        "yesPossible" : "possible",
        "note": ""
      },
      {
        "cdnIntegration" : "BYO CDN",
        "actualCDN" : "Jstream Flash Streaming",
        "yesPossible" : "possible",
        "note": ""
      },
      {
        "cdnIntegration" : "BYO CDN",
        "actualCDN" : "Jstream PD",
        "yesPossible" : "possible",
        "note": ""
      },
      {
        "cdnIntegration" : "BYO CDN",
        "actualCDN" : "Jstream HTTP Streaming",
        "yesPossible" : "possible",
        "note": ""
      },
      {
        "cdnIntegration" : "BYO CDN",
        "actualCDN" : "Telefonica PD",
        "yesPossible" : "possible",
        "note": ""
      },
      {
        "cdnIntegration" : "BYO CDN",
        "actualCDN" : "Telefonica Flash Streaming",
        "yesPossible" : "possible",
        "note": ""
      },
      {
        "cdnIntegration" : "BYO CDN",
        "actualCDN" : "Telefonica HTTP Streaming",
        "yesPossible" : "possible",
        "note": ""
      },
      {
        "cdnIntegration" : "Remote Assets",
        "actualCDN" : "HTTP Streaming",
        "yesPossible" : "yes",
        "note": "Capability for remote assets delivery is dependent on the server delivering the video.  Brightcove has no control over these delivery and security mechanisms."
      }
    ],
    "FAXS VOD Flash" : [
      {
        "cdnIntegration" : "BC CDN",
        "actualCDN" : "Limelight Flash Streaming",
        "yesPossible" : "yes",
        "note": ""
      },
      {
        "cdnIntegration" : "BC CDN",
        "actualCDN" : "Limelight PD",
        "yesPossible" : "yes",
        "note": ""
      },
      {
        "cdnIntegration" : "BC CDN",
        "actualCDN" : "Akamai Flash Streaming",
        "yesPossible" : "yes",
        "note": ""
      },
      {
        "cdnIntegration" : "BC CDN",
        "actualCDN" : "Akamai PD",
        "yesPossible" : "yes",
        "note": ""
      },
      {
        "cdnIntegration" : "BC CDN",
        "actualCDN" : "Akamai HD 2.0",
        "yesPossible" : "possible",
        "note": ""
      },
      {
        "cdnIntegration" : "BYO CDN",
        "actualCDN" : "Limelight Flash Streaming",
        "yesPossible" : "yes",
        "note": ""
      },
      {
        "cdnIntegration" : "BYO CDN",
        "actualCDN" : "Limelight PD",
        "yesPossible" : "yes",
        "note": ""
      },
      {
        "cdnIntegration" : "BYO CDN",
        "actualCDN" : "Akamai Flash Streaming",
        "yesPossible" : "yes",
        "note": ""
      },
      {
        "cdnIntegration" : "BYO CDN",
        "actualCDN" : "Akamai PD",
        "yesPossible" : "yes",
        "note": ""
      },
      {
        "cdnIntegration" : "BYO CDN",
        "actualCDN" : "Akamai HD 2.0",
        "yesPossible" : "possible",
        "note": ""
      },
      {
        "cdnIntegration" : "BYO CDN",
        "actualCDN" : "Level 3 PD",
        "yesPossible" : "possible",
        "note": ""
      },
      {
        "cdnIntegration" : "BYO CDN",
        "actualCDN" : "Level 3 HTTP Streaming",
        "yesPossible" : "possible",
        "note": ""
      },
      {
        "cdnIntegration" : "BYO CDN",
        "actualCDN" : "Highwinds PD",
        "yesPossible" : "possible",
        "note": ""
      },
      {
        "cdnIntegration" : "BYO CDN",
        "actualCDN" : "ChinaCache PD",
        "yesPossible" : "possible",
        "note": "China delivery only. Requires another CDN for outside China. Must have multiple accounts, and media sharing is not functional."
      },
      {
        "cdnIntegration" : "BYO CDN",
        "actualCDN" : "ChinaCache Flash Streaming",
        "yesPossible" : "yes",
        "note": "China delivery only. Requires another CDN for outside China. Must have multiple accounts, and media sharing is not functional."
      },
      {
        "cdnIntegration" : "BYO CDN",
        "actualCDN" : "Jstream PD",
        "yesPossible" : "possible",
        "note": ""
      },
      {
        "cdnIntegration" : "BYO CDN",
        "actualCDN" : "Jstream HTTP Streaming",
        "yesPossible" : "possible",
        "note": ""
      },
      {
        "cdnIntegration" : "BYO CDN",
        "actualCDN" : "Telefonica Flash Streaming",
        "yesPossible" : "possible",
        "note": ""
      },
      {
        "cdnIntegration" : "Remote Assets",
        "actualCDN" : "Flash Streaming",
        "yesPossible" : "possible",
        "note": "Capability for remote assets delivery is dependent on the server delivering the video.  Brightcove has no control over these delivery and security mechanisms."
      },
      {
        "cdnIntegration" : "Remote Assets",
        "actualCDN" : "PD",
        "yesPossible" : "possible",
        "note": "Capability for remote assets delivery is dependent on the server delivering the video.  Brightcove has no control over these delivery and security mechanisms."
      },
      {
        "cdnIntegration" : "Remote Assets",
        "actualCDN" : "HTTP Streaming",
        "yesPossible" : "yes",
        "note": "Capability for remote assets delivery is dependent on the server delivering the video.  Brightcove has no control over these delivery and security mechanisms."
      }
    ],
    "Widevine VOD Flash" : [
      {
        "cdnIntegration" : "BC CDN",
        "actualCDN" : "Limelight PD",
        "yesPossible" : "possible",
        "note": ""
      },
      {
        "cdnIntegration" : "BC CDN",
        "actualCDN" : "Akamai PD",
        "yesPossible" : "possible",
        "note": ""
      },
      {
        "cdnIntegration" : "BC CDN",
        "actualCDN" : "Akamai HD 2.0",
        "yesPossible" : "possible",
        "note": ""
      },
      {
        "cdnIntegration" : "BYO CDN",
        "actualCDN" : "Limelight PD",
        "yesPossible" : "possible",
        "note": ""
      },
      {
        "cdnIntegration" : "BYO CDN",
        "actualCDN" : "Akamai PD",
        "yesPossible" : "possible",
        "note": ""
      },
      {
        "cdnIntegration" : "BYO CDN",
        "actualCDN" : "Level 3 PD",
        "yesPossible" : "possible",
        "note": ""
      },
      {
        "cdnIntegration" : "BYO CDN",
        "actualCDN" : "Hightlight PD",
        "yesPossible" : "possible",
        "note": ""
      },
      {
        "cdnIntegration" : "BYO CDN",
        "actualCDN" : "ChinaCache PD",
        "yesPossible" : "possible",
        "note": "China delivery only. Requires another CDN for outside China. Must have multiple accounts, and media sharing is not functional."
      },
      {
        "cdnIntegration" : "BYO CDN",
        "actualCDN" : "Jstream PD",
        "yesPossible" : "possible",
        "note": ""
      },
      {
        "cdnIntegration" : "BYO CDN",
        "actualCDN" : "Telefonica PD",
        "yesPossible" : "possible",
        "note": ""
      },
      {
        "cdnIntegration" : "Remote Assets",
        "actualCDN" : "PD",
        "yesPossible" : "possible",
        "note": "Capability for remote assets delivery is dependent on the server delivering the video.  Brightcove has no control over these delivery and security mechanisms."
      }
    ],
    "RTMPe Live Flash" : [
      {
        "cdnIntegration" : "BC CDN",
        "actualCDN" : "Akamai Flash Streaming",
        "yesPossible" : "yes",
        "note": ""
      },
      {
        "cdnIntegration" : "BC CDN",
        "actualCDN" : "Limelight Flash Streaming",
        "yesPossible" : "yes",
        "note": ""
      }
    ],
    "SWFv Live Flash" : [
      {
        "cdnIntegration" : "BC CDN",
        "actualCDN" : "Limelight Flash Streaming",
        "yesPossible" : "yes",
        "note": ""
      },
      {
        "cdnIntegration" : "BC CDN",
        "actualCDN" : "Akamai Flash Streaming",
        "yesPossible" : "yes",
        "note": ""
      },
      {
        "cdnIntegration" : "Remote Assets",
        "actualCDN" : "PD",
        "yesPossible" : "possible",
        "note": "Capability for remote assets delivery is dependent on the server delivering the video.  Brightcove has no control over these delivery and security mechanisms."
      }
    ],
    "TTL Live Flash" : [
      {
        "cdnIntegration" : "BC CDN",
        "actualCDN" : "Limelight Flash Streaming",
        "yesPossible" : "yes",
        "note": ""
      },
      {
        "cdnIntegration" : "BC CDN",
        "actualCDN" : "Akamai Flash Streaming",
        "yesPossible" : "yes",
        "note": ""
      },
      {
        "cdnIntegration" : "BC CDN",
        "actualCDN" : "Akamai HD",
        "yesPossible" : "yes",
        "note": ""
      },
      {
        "cdnIntegration" : "BC CDN",
        "actualCDN" : "Akamai PD",
        "yesPossible" : "yes",
        "note": ""
      },
      {
        "cdnIntegration" : "BC CDN",
        "actualCDN" : "Akamai HD HTTPs",
        "yesPossible" : "yes",
        "note": ""
      },
      {
        "cdnIntegration" : "BYO CDN",
        "actualCDN" : "Akamai HD 2.0",
        "yesPossible" : "yes",
        "note": ""
      },
      {
        "cdnIntegration" : "Remote Assets",
        "actualCDN" : "Flash Streaming",
        "yesPossible" : "yes",
        "note": "Capability for remote assets delivery is dependent on the server delivering the video.  Brightcove has no control over these delivery and security mechanisms."
      },
      {
        "cdnIntegration" : "Remote Assets",
        "actualCDN" : "HTTP Streaming",
        "yesPossible" : "yes",
        "note": "Capability for remote assets delivery is dependent on the server delivering the video.  Brightcove has no control over these delivery and security mechanisms."
      }
    ],
    "TTL VOD HTML5" : [
      {
        "cdnIntegration" : "BC CDN",
        "actualCDN" : "Limelight PD",
        "yesPossible" : "yes",
        "note": ""
      },
      {
        "cdnIntegration" : "BC CDN",
        "actualCDN" : "Akamai PD",
        "yesPossible" : "yes",
        "note": ""
      },
      {
        "cdnIntegration" : "BYO CDN",
        "actualCDN" : "Limelight PD",
        "yesPossible" : "possible",
        "note": ""
      },
      {
        "cdnIntegration" : "BYO CDN",
        "actualCDN" : "Akamai Flash Streaming",
        "yesPossible" : "possible",
        "note": ""
      },
      {
        "cdnIntegration" : "BYO CDN",
        "actualCDN" : "Akamai HD",
        "yesPossible" : "possible",
        "note": ""
      },
      {
        "cdnIntegration" : "BYO CDN",
        "actualCDN" : "Akamai PD",
        "yesPossible" : "possible",
        "note": ""
      },
      {
        "cdnIntegration" : "BYO CDN",
        "actualCDN" : "Akamai HD 2.0",
        "yesPossible" : "yes",
        "note": ""
      }
    ],
    "eHLS VOD HTML5" : [
      {
        "cdnIntegration" : "BC CDN",
        "actualCDN" : "Limelight PD",
        "yesPossible" : "yes",
        "note": ""
      },
      {
        "cdnIntegration" : "BC CDN",
        "actualCDN" : "Akamai HD",
        "yesPossible" : "yes",
        "note": ""
      },
      {
        "cdnIntegration" : "BC CDN",
        "actualCDN" : "Akamai PD",
        "yesPossible" : "yes",
        "note": ""
      },
      {
        "cdnIntegration" : "BC CDN",
        "actualCDN" : "Akamai HD HTTPs",
        "yesPossible" : "yes",
        "note": ""
      },
      {
        "cdnIntegration" : "BC CDN",
        "actualCDN" : "Akamai HD 2.0",
        "yesPossible" : "yes",
        "note": ""
      },
      {
        "cdnIntegration" : "BYO CDN",
        "actualCDN" : "Akamai HD",
        "yesPossible" : "yes",
        "note": ""
      },
      {
        "cdnIntegration" : "BYO CDN",
        "actualCDN" : "Akamai HD 2.0",
        "yesPossible" : "yes",
        "note": ""
      },
      {
        "cdnIntegration" : "BYO CDN",
        "actualCDN" : "Level 3 HTTP Streaming",
        "yesPossible" : "yes",
        "note": ""
      },
      {
        "cdnIntegration" : "BYO CDN",
        "actualCDN" : "ChinaCache PD",
        "yesPossible" : "possible",
        "note": "China delivery only. Requires another CDN for outside China. Must have multiple accounts, and media sharing is not functional."
      },
      {
        "cdnIntegration" : "BYO CDN",
        "actualCDN" : "Jstream HTTP Streaming",
        "yesPossible" : "yes",
        "note": ""
      },
      {
        "cdnIntegration" : "BYO CDN",
        "actualCDN" : "Telefonica HTTP Streaming",
        "yesPossible" : "possible",
        "note": ""
      }
    ],
    "TTL Live HTML5" : [
      {
        "cdnIntegration" : "BC CDN",
        "actualCDN" : "Akamai HD",
        "yesPossible" : "yes",
        "note": ""
      },
      {
        "cdnIntegration" : "BC CDN",
        "actualCDN" : "Akamai PD",
        "yesPossible" : "yes",
        "note": ""
      },
      {
        "cdnIntegration" : "BC CDN",
        "actualCDN" : "Akamai HD HTTPs",
        "yesPossible" : "yes",
        "note": ""
      },
      {
        "cdnIntegration" : "BC CDN",
        "actualCDN" : "Akamai HD 2.0",
        "yesPossible" : "yes",
        "note": ""
      },
      {
        "cdnIntegration" : "BYO CDN",
        "actualCDN" : "Limelight PD",
        "yesPossible" : "possible",
        "note": ""
      },
      {
        "cdnIntegration" : "BYO CDN",
        "actualCDN" : "Akamai Flash Streaming",
        "yesPossible" : "possible",
        "note": ""
      },
      {
        "cdnIntegration" : "BYO CDN",
        "actualCDN" : "Akamai HD",
        "yesPossible" : "possible",
        "note": ""
      },
      {
        "cdnIntegration" : "BYO CDN",
        "actualCDN" : "Akamai PD",
        "yesPossible" : "possible",
        "note": ""
      },
      {
        "cdnIntegration" : "BYO CDN",
        "actualCDN" : "Akamai HD 2.0",
        "yesPossible" : "possible",
        "note": ""
      }
    ]
  }
}