{
  "account_id" : 1232842446001,
  "archive_master" : true,
  "name" : "dash-CENC",
  "description" : "This will produce 4 dash renditions with CENC",
  "renditions" : [
      {
		"media_type" : "video",
		"reference_id" : "av0",
		"format" : "m4f",
		"audio_codec" : "aac",
		"audio_bitrate" : 64,
		"video_bitrate":100,
		"width":"400",
		"height":"300",
		"fixed_keyframe_interval":true,
		"frame_rate": 15,
		"video_codec":"h264",
		"h264_profile" : "baseline",
        "keyframe_rate" : 0.5,
		"type": "segmented"
      },{
		"media_type" : "video",
		"reference_id" : "av1",
		"format" : "m4f",
		"audio_codec" : "aac",
		"audio_bitrate" : 64,
		"video_bitrate":436,
		"width":"480",
		"height":"360",
		"fixed_keyframe_interval":true,
		"frame_rate": 15,
		"video_codec":"h264",
		"h264_profile" : "baseline",
        "keyframe_rate" : 0.5,
		"type": "segmented"
      },{
		"media_type" : "video",
		"reference_id" : "av2",
		"format" : "m4f",
		"audio_codec" : "aac",
		"audio_bitrate" : 96,
		"video_bitrate":704,
		"width":"640",
		"height":"480",
		"fixed_keyframe_interval":true,
		"frame_rate": 15,
		"video_codec":"h264",
		"h264_profile" : "baseline",
        "keyframe_rate" : 0.5,
		"type": "segmented"
      },{
		"media_type" : "video",
		"reference_id" : "av3",
		"format" : "m4f",
		"audio_codec" : "aac",
		"audio_bitrate" : 128,
		"video_bitrate":1672,
		"width":"800",
		"height":"600",
		"fixed_keyframe_interval":true,
		"frame_rate": 15,
		"video_codec":"h264",
		"h264_profile" : "baseline",
        "keyframe_rate" : 0.5,
		"type": "segmented"
      }
  ],
  
  "packages": [
           {
               "drm": [ "marlin", "playready" ],
			   "package_type": "dash",
               "renditions": [ "av0" ]
           },
		   {
               "drm": [ "marlin", "playready" ],
			   "package_type": "dash",
               "renditions": [ "av1" ]
           },
		   {
               "drm": [ "marlin", "playready" ],
			   "package_type": "dash",
               "renditions": [ "av2" ]
           },
		   {
               "drm": [ "marlin", "playready" ],
			   "package_type": "dash",
               "renditions": [ "av3" ]
           }
       ]

}
