{
    "mobile-sdks": {
        "items": [
            {
                "name": "Player SDK for iOS",
                "items": [
                    {
                        "url": "//docs.brightcove.com/en/video-cloud/mobile-sdks/brightcove-player-sdk-for-ios/index.html",
                        "name": "Overview: Player SDK for iOS"
                    },
                    {
                        "items": [
                            {
                                "url": "//docs.brightcove.com/en/video-cloud/mobile-sdks/brightcove-player-sdk-for-ios/getting-started/overview.html",
                                "name": "Player SDK for iOS Overview"
                            },
                            {
                                "url": "//docs.brightcove.com/en/video-cloud/mobile-sdks/brightcove-player-sdk-for-ios/getting-started/registration.html",
                                "name": "Brightcove Registration"
                            },
                            {
                                "url": "//docs.brightcove.com/en/video-cloud/mobile-sdks/brightcove-player-sdk-for-ios/getting-started/content.html",
                                "name": "Working with Media Content"
                            },
                            {
                                "url": "//docs.brightcove.com/en/video-cloud/mobile-sdks/brightcove-player-sdk-for-ios/getting-started/understanding-events.html",
                                "name": "Understanding Events"
                            },
                            {
                                "url": "//docs.brightcove.com/en/video-cloud/mobile-sdks/brightcove-player-sdk-for-ios/guides/quick-start.html",
                                "name": "Quick Start Obj-C: Simple Video App"
                            },
                            {
                                "url": "//docs.brightcove.com/en/video-cloud/mobile-sdks/brightcove-player-sdk-for-ios/guides/quick-start-swift.html",
                                "name": "Quick Start Swift: Simple Video App"
                            }
                        ],
                        "name": "Getting Started"
                    },
                    {
                        "items": [
                            {
                                "url": "//docs.brightcove.com/en/video-cloud/mobile-sdks/brightcove-player-sdk-for-ios/reference/current/index.html",
                                "name": "Brightcove Player SDK for iOS"
                            },
                            {
                                "url": "//docs.brightcove.com/en/video-cloud/mobile-sdks/brightcove-player-sdk-for-ios/plugins/fairplay/reference/current/index.html",
                                "name": "FairPlay"
                            },
                            {
                                "url": "//docs.brightcove.com/en/video-cloud/mobile-sdks/brightcove-player-sdk-for-ios/plugins/freewheel/reference/current/index.html",
                                "name": "FreeWheel Plugin"
                            },
                            {
                                "url": "//docs.brightcove.com/en/video-cloud/mobile-sdks/brightcove-player-sdk-for-ios/plugins/ima/reference/current/index.html",
                                "name": "IMA Plugin"
                            },
                            {
                                "url": "//docs.brightcove.com/en/video-cloud/mobile-sdks/brightcove-player-sdk-for-ios/plugins/omniture/reference/current/index.html",
                                "name": "Omniture Plugin"
                            },
                            {
                                "url": "//docs.brightcove.com/en/video-cloud/mobile-sdks/brightcove-player-sdk-for-ios/plugins/onceux/reference/current/index.html",
                                "name": "Once UX Plugin"
                            },
                            {
                                "url": "//docs.brightcove.com/en/video-cloud/mobile-sdks/brightcove-player-sdk-for-ios/plugins/playerui/reference/current/index.html",
                                "name": "Player UI Plugin"
                            },
                            {
                                "url": "//docs.brightcove.com/en/video-cloud/mobile-sdks/brightcove-player-sdk-for-ios/plugins/sidecar-subtitles/reference/current/index.html",
                                "name": "Sidecar Subtitles"
                            },
                            {
                                "url": "//docs.brightcove.com/en/video-cloud/mobile-sdks/brightcove-player-sdk-for-ios/plugins/widevine/reference/current/index.html",
                                "name": "Widevine Plugin (current)"
                            },
                            {
                                "url": "//docs.brightcove.com/en/video-cloud/mobile-sdks/brightcove-player-sdk-for-ios/plugins/widevine/reference/versions/1.0.10/index.html",
                                "name": "Widevine Plugin (1.0.10)"
                            }
                        ],
                        "name": "References",
                        "url": "//docs.brightcove.com/en/video-cloud/mobile-sdks/brightcove-player-sdk-for-ios/references.html"
                    },
                    {
                        "items": [
                            {
                                "url": "//docs.brightcove.com/en/video-cloud/mobile-sdks/guides/drm.html",
                                "name": "Content Security (DRM)"
                            },
                            {
                                "url": "//docs.brightcove.com/en/video-cloud/mobile-sdks/brightcove-player-sdk-for-ios/guides/rendition-selection.html",
                                "name": "Rendition Selection"
                            },
                            {
                                "url": "//docs.brightcove.com/en/video-cloud/mobile-sdks/brightcove-player-sdk-for-ios/guides/resize-view.html",
                                "name": "Resizing the View"
                            },
                            {
                                "url": "//docs.brightcove.com/en/video-cloud/mobile-sdks/brightcove-player-sdk-for-ios/guides/analytics/analytics.html",
                                "name": "Using Brightcove Analytics"
                            },
                            {
                                "url": "//docs.brightcove.com/en/video-cloud/mobile-sdks/guides/view-analytics.html",
                                "name": "Viewing Brightcove Analytics"
                            },
                            {
                                "url": "//docs.brightcove.com/en/video-cloud/mobile-sdks/brightcove-player-sdk-for-ios/guides/webvtt-captions.html",
                                "name": "Using WebVTT Captions"
                            },
                            {
                                "url": "//docs.brightcove.com/en/video-cloud/mobile-sdks/brightcove-player-sdk-for-ios/guides/ats.html",
                                "name": "Working with App Transport Security (ATS)"
                            }
                        ],
                        "name": "Guides",
                        "url": "//docs.brightcove.com/en/video-cloud/mobile-sdks/brightcove-player-sdk-for-ios/guides.html"
                    },
                    {
                        "items": [
                            {
                                "url": "https://github.com/BrightcoveOS/ios-player-samples",
                                "name": "Basic iOS Player Samples"
                            },
                            {
                                "url": "//docs.brightcove.com/en/video-cloud/mobile-sdks/brightcove-player-sdk-for-ios/samples/code-examples.html",
                                "name": "Code Snippets"
                            }
                        ],
                        "name": "Code Samples"
                    }
                ]
            },
            {
                "name": "Player SDK for tvOS",
                "items": [
                    {
                        "url": "//docs.brightcove.com/en/video-cloud/mobile-sdks/brightcove-player-sdk-for-tvos/index.html",
                        "name": "Overview: Player SDK for tvOS"
                    },
                    {
                        "items": [
                            {
                                "url": "//docs.brightcove.com/en/video-cloud/mobile-sdks/brightcove-player-sdk-for-tvos/getting-started/quick-start-tvos-swift.html",
                                "name": "Quick Start Swift: Simple Video App"
                            }
                        ],
                        "name": "Getting Started"
                    },
                    {
                        "items": [
                            {
                                "url": "//docs.brightcove.com/en/video-cloud/mobile-sdks/brightcove-player-sdk-for-ios/reference/current/index.html",
                                "name": "Brightcove Player SDK for iOS"
                            },
                            {
                                "url": "//docs.brightcove.com/en/video-cloud/mobile-sdks/brightcove-player-sdk-for-ios/plugins/fairplay/reference/current/index.html",
                                "name": "FairPlay"
                            },
                            {
                                "url": "//docs.brightcove.com/en/video-cloud/mobile-sdks/brightcove-player-sdk-for-ios/plugins/sidecar-subtitles/reference/current/index.html",
                                "name": "Sidecar Subtitles"
                            }
                        ],
                        "name": "References",
                        "url": "//docs.brightcove.com/en/video-cloud/mobile-sdks/brightcove-player-sdk-for-ios/references.html"
                    },
                    {
                        "items": [
                            {
                                "url": "//docs.brightcove.com/en/video-cloud/mobile-sdks/guides/drm.html",
                                "name": "Content Security (DRM)"
                            },
                            {
                                "url": "//docs.brightcove.com/en/video-cloud/mobile-sdks/brightcove-player-sdk-for-ios/guides/analytics/analytics.html",
                                "name": "Using Brightcove Analytics"
                            },
                            {
                                "url": "//docs.brightcove.com/en/video-cloud/mobile-sdks/guides/view-analytics.html",
                                "name": "Viewing Brightcove Analytics"
                            },
                            {
                                "url": "//docs.brightcove.com/en/video-cloud/mobile-sdks/brightcove-player-sdk-for-ios/guides/webvtt-captions.html",
                                "name": "Using WebVTT Captions"
                            },
                            {
                                "url": "//docs.brightcove.com/en/video-cloud/mobile-sdks/brightcove-player-sdk-for-ios/guides/ats.html",
                                "name": "Working with App Transport Security (ATS)"
                            }
                        ],
                        "name": "Guides"
                    },
                    {
                        "items": [
                            {
                                "url": "https://github.com/BrightcoveOS/ios-player-samples/tree/master/Player/AppleTV",
                                "name": "Basic tvOS Player Sample"
                            }
                        ],
                        "name": "Code Samples"
                    }
                ]
            },
            {
                "name": "Player SDK for Android",
                "items": [
                    {
                        "url": "//docs.brightcove.com/en/video-cloud/mobile-sdks/brightcove-player-sdk-for-android/index.html",
                        "name": "Overview: Player SDK for Android"
                    },
                    {
                        "items": [
                            {
                                "url": "//docs.brightcove.com/en/video-cloud/mobile-sdks/brightcove-player-sdk-for-android/getting-started/overview.html",
                                "name": "Player SDK for Android Overview"
                            },
                            {
                                "url": "//docs.brightcove.com/en/video-cloud/mobile-sdks/brightcove-player-sdk-for-android/getting-started/brightcoveplayer.html",
                                "name": "Understanding BrightcovePlayer"
                            },
                            {
                                "url": "//docs.brightcove.com/en/video-cloud/mobile-sdks/brightcove-player-sdk-for-android/getting-started/basevideoview.html",
                                "name": "Choosing a Video View"
                            },
                            {
                                "url": "//docs.brightcove.com/en/video-cloud/mobile-sdks/brightcove-player-sdk-for-android/getting-started/registration.html",
                                "name": "Brightcove Registration"
                            },
                            {
                                "url": "//docs.brightcove.com/en/video-cloud/mobile-sdks/brightcove-player-sdk-for-android/getting-started/content.html",
                                "name": "Working with Media Content"
                            },
                            {
                                "url": "//docs.brightcove.com/en/video-cloud/mobile-sdks/brightcove-player-sdk-for-android/getting-started/understanding-events.html",
                                "name": "Understanding Events"
                            },
                            {
                                "url": "//docs.brightcove.com/en/video-cloud/mobile-sdks/brightcove-player-sdk-for-android/guides/studio-android-sdk-quick-start.html",
                                "name": "Brightcove Player SDK for Android Quick Start"
                            }
                        ],
                        "name": "Getting Started"
                    },
                    {
                        "name": "References",
                        "items": [
                            {
                                "url": "//docs.brightcove.com/en/video-cloud/mobile-sdks/brightcove-player-sdk-for-android/reference/current/javadoc/index.html",
                                "name": "Brightcove Player SDK for Android"
                            },
                            {
                                "url": "//docs.brightcove.com/en/video-cloud/mobile-sdks/brightcove-player-sdk-for-android/reference/current/javadoc/com/brightcove/cast/package-frame.html",
                                "name": "Cast Component"
                            },
                            {
                                "url": "//docs.brightcove.com/en/video-cloud/mobile-sdks/brightcove-player-sdk-for-android/reference/current/javadoc/com/brightcove/freewheel/controller/package-frame.html",
                                "name": "FreeWheel Component"
                            },
                            {
                                "url": "//docs.brightcove.com/en/video-cloud/mobile-sdks/brightcove-player-sdk-for-android/reference/current/javadoc/com/brightcove/ima/package-frame.html",
                                "name": "IMA Plugin"
                            },
                            {
                                "url": "//docs.brightcove.com/en/video-cloud/mobile-sdks/brightcove-player-sdk-for-android/reference/current/javadoc/com/brightcove/omniture/package-frame.html",
                                "name": "Omniture Plugin"
                            },
                            {
                                "url": "//docs.brightcove.com/en/video-cloud/mobile-sdks/brightcove-player-sdk-for-android/reference/current/javadoc/com/brightcove/onceux/package-frame.html",
                                "name": "Once UX Plugin"
                            },
                            {
                                "url": "//docs.brightcove.com/en/video-cloud/mobile-sdks/brightcove-player-sdk-for-android/reference/current/javadoc/com/brightcove/drm/widevine/package-frame.html",
                                "name": "Widevine Plugin"
                            }
                        ]
                    },
                    {
                        "items": [
                            {
                                "url": "//docs.brightcove.com/en/video-cloud/mobile-sdks/brightcove-player-sdk-for-android/guides/view-layout.html",
                                "name": "Add View/Manage Layout"
                            },
                            {
                                "url": "//docs.brightcove.com/en/video-cloud/mobile-sdks/guides/drm.html",
                                "name": "Content Security (DRM)"
                            },
                            {
                                "url": "//docs.brightcove.com/en/video-cloud/mobile-sdks/brightcove-player-sdk-for-android/guides/error-msg-reference.html",
                                "name": "Error Message Guide"
                            },
                            {
                                "url": "//docs.brightcove.com/en/video-cloud/mobile-sdks/brightcove-player-sdk-for-android/guides/orientation-change/orientation-change.html",
                                "name": "Orientation Change"
                            },
                            {
                                "url": "//docs.brightcove.com/en/video-cloud/mobile-sdks/brightcove-player-sdk-for-android/guides/player-controls.html",
                                "name": "Player Controls"
                            },
                            {
                                "url": "//docs.brightcove.com/en/video-cloud/mobile-sdks/brightcove-player-sdk-for-android/guides/plugin-guide/plugin-guide.html",
                                "name": "Plugin Guide"
                            },
                            {
                                "url": "//docs.brightcove.com/en/video-cloud/mobile-sdks/brightcove-player-sdk-for-android/guides/rendition-selection.html",
                                "name": "Rendition Selection"
                            },
                            {
                                "url": "//docs.brightcove.com/en/video-cloud/mobile-sdks/brightcove-player-sdk-for-android/guides/analytics/analytics.html",
                                "name": "Using Brightcove Analytics"
                            },
                            {
                                "url": "//docs.brightcove.com/en/video-cloud/mobile-sdks/guides/view-analytics.html",
                                "name": "Viewing Brightcove Analytics"
                            }
                        ],
                        "name": "Guides",
                        "url": "//docs.brightcove.com/en/video-cloud/mobile-sdks/brightcove-player-sdk-for-android/guides/index.html"
                    },
                    {
                        "items": [
                            {
                                "name": "HLS Playback with the Player SDK",
                                "url": "//docs.brightcove.com/en/video-cloud/mobile-sdks/hls-player/guides/exoplayer.html"
                            },
                            {
                                "name": "HLS limitations without the Player SDK",
                                "url": "//docs.brightcove.com/en/video-cloud/mobile-sdks/hls-player/guides/hls-limitations.html"
                            }
                        ],
                        "name": "HLS Playback"
                    },
                    {
                        "items": [
                            {
                                "url": "//github.com/BrightcoveOS/android-player-samples",
                                "name": "Basic Android Player Samples"
                            },
                            {
                                "url": "//docs.brightcove.com/en/video-cloud/mobile-sdks/brightcove-player-sdk-for-android/samples/code-examples.html",
                                "name": "Code Snippets"
                            }
                        ],
                        "name": "Code Samples"
                    }
                ]
            },
            {
                "name": "Developer Support",
                "items": [
                    {
                        "url": "//groups.google.com/forum/#!forum/brightcove-native-player-sdks",
                        "name": "Player SDK Developer Forum"
                    },
                    {
                        "url": "//docs.brightcove.com/en/video-cloud/mobile-sdks/faq.html",
                        "name": "Player SDK FAQ"
                    },
                    {
                        "url": "//support.brightcove.com/en/video-cloud/docs/known-issues-studio-and-brightcove-player#sdks",
                        "name": "SDK Known Issues"
                    },
                    {
                        "url": "//docs.brightcove.com/en/video-cloud/mobile-sdks/report-issue.html",
                        "name": "Report an Issue"
                    }
                ]
            }
        ],
        "url": "//docs.brightcove.com/en/video-cloud/mobile-sdks/index.html",
        "name": "Mobile SDKs"
    }
}
